{
  "DigitalOutputSequences": [
    {
      "Name": "Blink DigitalOutput 500ms",
      "Description": "Blink DigitalOutput every 500ms",
      "UsageNotes":  "Must specify HubPort and Channel",
      "Actions": [
        { "DigitalOut": true, "Duration": 500 },
        { "DigitalOut": false, "Duration": 500 },
        { "DigitalOut": true, "Duration": 500 },
        { "DigitalOut": false, "Duration": 500 },
      ]
    },
    {
      "Name": "Blink DigitalOutput 250ms",
      "Description": "Blink DigitalOutput every 250ms",
      "UsageNotes":  "Must specify HubPort and Channel",
      "Actions": [
        { "DigitalOut": true, "Duration": 250 },
        { "DigitalOut": false, "Duration": 250 },
        { "DigitalOut": true, "Duration": 250 },
        { "DigitalOut": false, "Duration": 250 },
        { "DigitalOut": true, "Duration": 250 },
        { "DigitalOut": false, "Duration": 250 },
        { "DigitalOut": true, "Duration": 250 },
        { "DigitalOut": false, "Duration": 250 },
      ]
    },
    {
      "Name": "Blink DO-HP0-C0",
      "HubPort": 0,
      "Channel": 0,
      "Description": "Blink DigitalOutput 0",
      "Actions": [
        { "DigitalOut": true, "Duration": 500 },
        { "DigitalOut": false, "Duration": 500 },
        { "DigitalOut": true, "Duration": 500 },
        { "DigitalOut": false, "Duration": 500 },
      ]
    },
    {
      "Name": "Blink DO-HP1-C0",
      "Description": "Blink DigitalOutput 0",
      "HubPort": 1,
      "Channel": 0,
      "Actions": [
        { "DigitalOut": true, "Duration": 500 },
        { "DigitalOut": false, "Duration": 500 },
        { "DigitalOut": true, "Duration": 500 },
        { "DigitalOut": false, "Duration": 500 },
      ]
    }, 
  ]
}